setup.cfg
setup.py
maintenance_mode/__init__.py
maintenance_mode/context_processors.py
maintenance_mode/core.py
maintenance_mode/io.py
maintenance_mode/middleware.py
maintenance_mode/settings.py
maintenance_mode/urls.py
maintenance_mode/utils.py
maintenance_mode/version.py
maintenance_mode/views.py
maintenance_mode/management/__init__.py
maintenance_mode/management/commands/__init__.py
maintenance_mode/management/commands/maintenance_mode.py
nereo_django_maintenance_mode.egg-info/PKG-INFO
nereo_django_maintenance_mode.egg-info/SOURCES.txt
nereo_django_maintenance_mode.egg-info/dependency_links.txt
nereo_django_maintenance_mode.egg-info/top_level.txt