Metadata-Version: 1.1
Name: nereo-django-maintenance-mode
Version: 0.6.1
Summary: django-maintenance-mode shows a 503 error page when maintenance-mode is on.
Home-page: https://github.com/Nereo/django-maintenance-mode
Author: Francois Voron
Author-email: francois.voron@nereo.fr
License: UNKNOWN
Download-URL: https://github.com/Nereo/django-maintenance-mode/archive/0.6.1.tar.gz
Keywords: django,maintenance,mode,offline,under,503,service,temporarily,unavailable
Platform: UNKNOWN
Requires: django(>=1.4)
